hgate/__init__.py
hgate/a1.py
hgate/a2.py
hgate/main.py
hgate-0.0.1.dist-info/License
hgate-0.0.1.dist-info/METADATA
hgate-0.0.1.dist-info/WHEEL
hgate-0.0.1.dist-info/top_level.txt
hgate-0.0.1.dist-info/RECORD
